HdlLib/Drawing.py
HdlLib/EvalResources.py
HdlLib/GUIGeneric.py
HdlLib/Graphics.py
HdlLib/TBGen.py
HdlLib/VHDLParser.py
HdlLib/__init__.py
HdlLib/__main__.py
HdlLib/SysGen/Assignment.py
HdlLib/SysGen/Condition.py
HdlLib/SysGen/Constraints.py
HdlLib/SysGen/FiniteStateMachine.py
HdlLib/SysGen/FpgaOperations.py
HdlLib/SysGen/HDLEditor.py
HdlLib/SysGen/Interface.py
HdlLib/SysGen/LibEditor.py
HdlLib/SysGen/Module.py
HdlLib/SysGen/PackageBuilder.py
HdlLib/SysGen/Protocol.py
HdlLib/SysGen/Service.py
HdlLib/SysGen/Signal.py
HdlLib/SysGen/Simulation.py
HdlLib/SysGen/Verify.py
HdlLib/SysGen/XmlLibManager.py
HdlLib/SysGen/__init__.py
HdlLib/SysGen/__main__.py
HdlLib/SysGen/HW/HwConstraints.py
HdlLib/SysGen/HW/HwLib.py
HdlLib/SysGen/HW/HwModel.py
HdlLib/SysGen/HW/HwResources.py
HdlLib/SysGen/HW/__init__.py
HdlLib/Utilities/BugManager.py
HdlLib/Utilities/ColoredLogging.py
HdlLib/Utilities/ConsoleInterface.py
HdlLib/Utilities/DataMining.py
HdlLib/Utilities/DesignTree.py
HdlLib/Utilities/ErrorHandlers.py
HdlLib/Utilities/ExtensionSilence.py
HdlLib/Utilities/GUITools.py
HdlLib/Utilities/HtmlTextView.py
HdlLib/Utilities/Misc.py
HdlLib/Utilities/PlotViewer.py
HdlLib/Utilities/RemoteOperations.py
HdlLib/Utilities/SafeRun.py
HdlLib/Utilities/Threads.py
HdlLib/Utilities/Timer.py
HdlLib/Utilities/UserConfig.py
HdlLib/Utilities/__init__.py
HdlLib-0.1.1.dist-info/DESCRIPTION.rst
HdlLib-0.1.1.dist-info/METADATA
HdlLib-0.1.1.dist-info/RECORD
HdlLib-0.1.1.dist-info/WHEEL
HdlLib-0.1.1.dist-info/metadata.json
HdlLib-0.1.1.dist-info/top_level.txt
