Metadata-Version: 2.0
Name: HdlLib
Version: 0.1.1
Summary: VHDL source management : parse, organize, assemble, generate testbenches
Home-page: https://gitlab.com/Yabolo/HdlLib
Author: Matthieu PAYET
Author-email: matthieu.payet@free.fr
License: GPLv3
Keywords: FPGA VHDL IP testbench test parser circuit system design RTL HDL
Platform: UNKNOWN
Classifier: Development Status :: 3 - Alpha
Classifier: Intended Audience :: Developers
Classifier: Topic :: Software Development :: Build Tools
Classifier: License :: OSI Approved :: GNU General Public License v3 (GPLv3)
Classifier: Programming Language :: Python :: 3
Classifier: Programming Language :: Python :: 3.3
Classifier: Programming Language :: Python :: 3.4
Classifier: Programming Language :: Python :: 3.5
Requires-Dist: cairosvg
Requires-Dist: cffi
Requires-Dist: lxml
Provides-Extra: dev
Requires-Dist: check-manifest; extra == 'dev'
Provides-Extra: test
Requires-Dist: coverage; extra == 'test'
